hashranking/__init__.py
hashranking/cpp_extension_wrapper.py
hashranking/hashranking_cpp.pyd
hashranking/numpy_implementation.py
hashranking-0.0.1.dist-info/DESCRIPTION.rst
hashranking-0.0.1.dist-info/METADATA
hashranking-0.0.1.dist-info/RECORD
hashranking-0.0.1.dist-info/WHEEL
hashranking-0.0.1.dist-info/metadata.json
hashranking-0.0.1.dist-info/top_level.txt
