Metadata-Version: 2.0
Name: hashranking
Version: 0.0.1
Summary: fast procedures for forking with hashes
Home-page: https://github.com/podgorskiy/hashranking
Author: Stanislav Pidhorskyi
Author-email: stanislav@podgorskiy.com
License: MIT
Platform: UNKNOWN
Classifier: Development Status :: 3 - Alpha
Classifier: License :: OSI Approved :: MIT License
Classifier: Programming Language :: Python :: 2.7
Classifier: Programming Language :: Python :: 3.6
